{
  "ident": "(abaf3f53-5360-473c-85d7-b8ccca37fc85|demoman1000)",
  "lastTeleportOrigin": {
    "dim": 0,
    "pitch": 21.599577,
    "yaw": 208.35489,
    "xd": -183.2673978872069,
    "yd": 69.98929153197692,
    "zd": 197.88346323363535
  },
  "lastTeleportTime": 1552624495129,
  "selDim": 0,
  "inventoryGroups": {},
  "modInventoryGroups": {},
  "activeInventoryGroup": "default",
  "timePlayed": 28325854,
  "firstLogin": "Mar 14, 2019 4:36:30 AM",
  "lastLogin": "Mar 14, 2019 11:38:11 PM",
  "lastLogout": "Mar 15, 2019 5:08:40 AM",
  "namedTimeout": {}
}